titan/__init__.py
titan/agent.py
titan/distributions.py
titan/exposures/__init__.py
titan/exposures/base_exposure.py
titan/exposures/hiv.py
titan/exposures/knowledge.py
titan/exposures/monkeypox.py
titan/features/__init__.py
titan/features/base_feature.py
titan/features/external_exposure.py
titan/features/haart.py
titan/features/high_risk.py
titan/features/incar.py
titan/features/partner_tracing.py
titan/features/prep.py
titan/features/random_trial.py
titan/features/syringe_services.py
titan/features/vaccine.py
titan/interactions/__init__.py
titan/interactions/base_interaction.py
titan/interactions/injection.py
titan/interactions/pca.py
titan/interactions/sex.py
titan/location.py
titan/model.py
titan/output.py
titan/params/agent_zero.yml
titan/params/assort_mix.yml
titan/params/calibration.yml
titan/params/classes.yml
titan/params/demographics.yml
titan/params/enter_exit.yml
titan/params/exposures.yml
titan/params/external_exposure.yml
titan/params/features.yml
titan/params/haart.yml
titan/params/high_risk.yml
titan/params/hiv.yml
titan/params/incar.yml
titan/params/knowledge.yml
titan/params/location.yml
titan/params/model.yml
titan/params/monkeypox.yml
titan/params/outputs.yml
titan/params/partner_tracing.yml
titan/params/partnership.yml
titan/params/prep.yml
titan/params/random_trial.yml
titan/params/syringe_services.yml
titan/params/timeline_scaling.yml
titan/params/vaccine.yml
titan/parse_params.py
titan/partnering.py
titan/population.py
titan/population_io.py
titan/probabilities.py
titan/run_titan.py
titan/settings/atlanta/assort_mix.yml
titan/settings/atlanta/calibration.yml
titan/settings/atlanta/demographics.yml
titan/settings/atlanta/model.yml
titan/settings/atlanta/outputs.yml
titan/settings/atlanta/partnership.yml
titan/settings/atlanta-latino/assort_mix.yml
titan/settings/atlanta-latino/calibration.yml
titan/settings/atlanta-latino/demographics.yml
titan/settings/atlanta-latino/model.yml
titan/settings/atlanta-latino/outputs.yml
titan_model-3.3.2.dist-info/LICENSE
titan_model-3.3.2.dist-info/METADATA
titan_model-3.3.2.dist-info/WHEEL
titan_model-3.3.2.dist-info/entry_points.txt
titan_model-3.3.2.dist-info/RECORD
