Metadata-Version: 2.1
Name: titan-model
Version: 3.3.2
Summary: TITAN Agent Based Model
Home-page: https://titanmodel.org
License: GPL-3.0-only
Author: Sam Bessey
Author-email: sam_bessey@brown.edu
Requires-Python: >=3.9,<4.0
Classifier: License :: OSI Approved :: GNU General Public License v3 (GPLv3)
Classifier: Operating System :: OS Independent
Classifier: Programming Language :: Python :: 3
Classifier: Programming Language :: Python :: 3.9
Classifier: Programming Language :: Python :: 3.10
Classifier: Programming Language :: Python :: 3.11
Classifier: Programming Language :: Python :: 3.12
Provides-Extra: docs
Provides-Extra: linting
Requires-Dist: black (>=23.1.0,<24.0.0) ; extra == "linting"
Requires-Dist: flake8 (>=3.8,<4.0) ; extra == "linting"
Requires-Dist: mkdocs (>=1.2.4,<2.0.0) ; extra == "docs"
Requires-Dist: mkdocs-material (>=9.5.26,<10.0.0) ; extra == "docs"
Requires-Dist: mkdocstrings[python] (>=0.25.1,<0.26.0) ; extra == "docs"
Requires-Dist: mypy (>=1.0.0,<2.0.0) ; extra == "linting"
Requires-Dist: nanoid (>=2.0,<3.0)
Requires-Dist: networkx (>=2.4,<3.0)
Requires-Dist: numpy (>=1.26,<2.0)
Requires-Dist: oyaml (>=1.0,<2.0)
Requires-Dist: paraml (>=0.1,<0.2)
Project-URL: Documentation, https://pph-collective.github.io/titan
Project-URL: Repository, https://github.com/pph-collective/TITAN
